common/MCPutil.py
common/TGtypes.py
common/__init__.py
common/azutils.py
common/common_def.py
common/common_types.py
common/filter_utils.py
common/geoutils.py
common/getip.py
common/mcpop.py
common/mcpre.py
common/v2_1def.py
common/volume_4D_Converter.py
rcs_common-0.2.5.dist-info/METADATA
rcs_common-0.2.5.dist-info/WHEEL
rcs_common-0.2.5.dist-info/dependency_links.txt
rcs_common-0.2.5.dist-info/top_level.txt
rcs_common-0.2.5.dist-info/RECORD
