Metadata-Version: 2.1
Name: rcs-common
Version: 0.2.5
Summary: Common directory of Airwayz Dev
Home-page: https://bitbucket.org/airwayzdev/common
License: UNKNOWN
Platform: UNKNOWN
Requires-Dist: awz-server-api-test
Requires-Dist: awz-client-api-test
Requires-Dist: swagger-ui-bundle (==0.0.9)
Requires-Dist: clickclick
Requires-Dist: jsonschema
Requires-Dist: inflection
Requires-Dist: openapi-spec-validator (==0.6.0)
Requires-Dist: numpy
Requires-Dist: pandas (>=1.5.2)
Requires-Dist: python-dateutil (>=2.8.2)
Requires-Dist: pytz (>=2022.6)
Requires-Dist: requests (>=2.28.1)
Requires-Dist: rtree (>=1.0.1)
Requires-Dist: scipy (>=1.11.1)
Requires-Dist: Shapely (>=1.8.5.post1)
